.gitignore
.travis.yml
README.md
changelog.md
distr.sh
license.txt
requirements_apt.txt
requirements_conda.txt
requirements_pip.txt
setup.cfg
setup.py
conda-recipe/bld.bat
conda-recipe/build.sh
conda-recipe/meta.yaml
sed3/__init__.py
sed3/sed3.py
sed3/sed3qt.py
sed3.egg-info/PKG-INFO
sed3.egg-info/SOURCES.txt
sed3.egg-info/dependency_links.txt
sed3.egg-info/top_level.txt
tests/sed_qt_test.py
tests/sed_test.py