Metadata-Version: 1.1
Name: sed3
Version: 1.4.1
Summary: 3D viewer and editor of color seeds
Home-page: https://github.com/mjirik/py3DSeedEditor
Author: Miroslav Jirik
Author-email: miroslav.jirik@gmail.com
License: MIT
Keywords: viewer 3D editor
Platform: UNKNOWN
Classifier: Development Status :: 3 - Alpha
Classifier: Intended Audience :: Developers
Classifier: Topic :: Scientific/Engineering :: Bio-Informatics
Classifier: License :: OSI Approved :: MIT License
Classifier: Programming Language :: Python :: 2.7
Classifier: Programming Language :: Python :: 3.4
